[
    [
        {
            "DocumentID": 30687184,
            "DocumentTypeID": 4,
            "DocumentTypeName": "ANNUAL REPORT - FULFILLED",
            "FileLocation": null,
            "FileLocationCorrespondence": "Certificates\\2024\\07\\0020608716_OnlineReport.pdf",
            "FileLocationReceipt": null,
            "CorrespondenceFileName": "0020608716_OnlineReport.pdf",
            "ReceiptFileName": null,
            "FilingNumber": 0,
            "TransactionID": 0,
            "WorkorderID": 0,
            "BusinessID": 0,
            "TrademarkID": 0,
            "RegistrationNo": 0,
            "IsOnline": false,
            "FilingDateTime": "2024-07-18T12:27:51",
            "FilerEmailAddress": null,
            "UserName": "MAHESH PANCHAL",
            "DocumentTable": "BUSINESSCORRESPONDENCE",
            "IsPublicVisible": false,
            "Source": "ONLINE",
            "CFTId": null,
            "CFTType": null,
            "NumberOfPages": 0,
            "UncommitedTID": 0,
            "CreatedDate": "0001-01-01T00:00:00",
            "FilerID": 0,
            "UserID": 0,
            "CreatedBy": 0,
            "IPAddress": null,
            "ModifiedBy": 0,
            "ModifiedIPAddress": null
        },
        {
            "DocumentID": 30687185,
            "DocumentTypeID": 27,
            "DocumentTypeName": "CONFIRMATION LETTER",
            "FileLocation": null,
            "FileLocationCorrespondence": "Certificates\\2024\\07\\0020608716_ConfirmationLetter.pdf",
            "FileLocationReceipt": null,
            "CorrespondenceFileName": "0020608716_ConfirmationLetter.pdf",
            "ReceiptFileName": null,
            "FilingNumber": 0,
            "TransactionID": 0,
            "WorkorderID": 0,
            "BusinessID": 0,
            "TrademarkID": 0,
            "RegistrationNo": 0,
            "IsOnline": false,
            "FilingDateTime": "2024-07-18T12:27:51",
            "FilerEmailAddress": null,
            "UserName": "MAHESH PANCHAL",
            "DocumentTable": "BUSINESSCORRESPONDENCE",
            "IsPublicVisible": false,
            "Source": "ONLINE",
            "CFTId": null,
            "CFTType": null,
            "NumberOfPages": 0,
            "UncommitedTID": 0,
            "CreatedDate": "0001-01-01T00:00:00",
            "FilerID": 0,
            "UserID": 0,
            "CreatedBy": 0,
            "IPAddress": null,
            "ModifiedBy": 0,
            "ModifiedIPAddress": null
        }
    ],
    [
        {
            "DocumentID": 26517641,
            "DocumentTypeID": 4,
            "DocumentTypeName": "ANNUAL REPORT - FULFILLED",
            "FileLocation": null,
            "FileLocationCorrespondence": "Certificates\\2023\\05\\0018544072_OnlineReport.pdf",
            "FileLocationReceipt": null,
            "CorrespondenceFileName": "0018544072_OnlineReport.pdf",
            "ReceiptFileName": null,
            "FilingNumber": 0,
            "TransactionID": 0,
            "WorkorderID": 0,
            "BusinessID": 0,
            "TrademarkID": 0,
            "RegistrationNo": 0,
            "IsOnline": false,
            "FilingDateTime": "2023-05-25T12:22:22",
            "FilerEmailAddress": null,
            "UserName": "",
            "DocumentTable": "BUSINESSCORRESPONDENCE",
            "IsPublicVisible": false,
            "Source": "ONLINE",
            "CFTId": null,
            "CFTType": null,
            "NumberOfPages": 0,
            "UncommitedTID": 0,
            "CreatedDate": "0001-01-01T00:00:00",
            "FilerID": 0,
            "UserID": 0,
            "CreatedBy": 0,
            "IPAddress": null,
            "ModifiedBy": 0,
            "ModifiedIPAddress": null
        }
    ],
    [
        {
            "DocumentID": 23221466,
            "DocumentTypeID": 4,
            "DocumentTypeName": "ANNUAL REPORT - FULFILLED",
            "FileLocation": null,
            "FileLocationCorrespondence": "Certificates\\2022\\06\\0016916779_OnlineReport.pdf",
            "FileLocationReceipt": null,
            "CorrespondenceFileName": "0016916779_OnlineReport.pdf",
            "ReceiptFileName": null,
            "FilingNumber": 0,
            "TransactionID": 0,
            "WorkorderID": 0,
            "BusinessID": 0,
            "TrademarkID": 0,
            "RegistrationNo": 0,
            "IsOnline": false,
            "FilingDateTime": "2022-06-08T10:23:21",
            "FilerEmailAddress": null,
            "UserName": "",
            "DocumentTable": "BUSINESSCORRESPONDENCE",
            "IsPublicVisible": false,
            "Source": "ONLINE",
            "CFTId": null,
            "CFTType": null,
            "NumberOfPages": 0,
            "UncommitedTID": 0,
            "CreatedDate": "0001-01-01T00:00:00",
            "FilerID": 0,
            "UserID": 0,
            "CreatedBy": 0,
            "IPAddress": null,
            "ModifiedBy": 0,
            "ModifiedIPAddress": null
        }
    ],
    [
        {
            "DocumentID": 20185879,
            "DocumentTypeID": 4,
            "DocumentTypeName": "ANNUAL REPORT - FULFILLED",
            "FileLocation": null,
            "FileLocationCorrespondence": "Certificates\\2021\\07\\0015385968_OnlineReport.pdf",
            "FileLocationReceipt": null,
            "CorrespondenceFileName": "0015385968_OnlineReport.pdf",
            "ReceiptFileName": null,
            "FilingNumber": 0,
            "TransactionID": 0,
            "WorkorderID": 0,
            "BusinessID": 0,
            "TrademarkID": 0,
            "RegistrationNo": 0,
            "IsOnline": false,
            "FilingDateTime": "2021-07-13T09:08:11",
            "FilerEmailAddress": null,
            "UserName": "MAHESH PANCHAL",
            "DocumentTable": "BUSINESSCORRESPONDENCE",
            "IsPublicVisible": false,
            "Source": "ONLINE",
            "CFTId": null,
            "CFTType": null,
            "NumberOfPages": 0,
            "UncommitedTID": 0,
            "CreatedDate": "0001-01-01T00:00:00",
            "FilerID": 0,
            "UserID": 0,
            "CreatedBy": 0,
            "IPAddress": null,
            "ModifiedBy": 0,
            "ModifiedIPAddress": null
        },
        {
            "DocumentID": 20185880,
            "DocumentTypeID": 27,
            "DocumentTypeName": "CONFIRMATION LETTER",
            "FileLocation": null,
            "FileLocationCorrespondence": "Certificates\\2021\\07\\0015385968_ConfirmationLetter.pdf",
            "FileLocationReceipt": null,
            "CorrespondenceFileName": "0015385968_ConfirmationLetter.pdf",
            "ReceiptFileName": null,
            "FilingNumber": 0,
            "TransactionID": 0,
            "WorkorderID": 0,
            "BusinessID": 0,
            "TrademarkID": 0,
            "RegistrationNo": 0,
            "IsOnline": false,
            "FilingDateTime": "2021-07-13T09:08:11",
            "FilerEmailAddress": null,
            "UserName": "MAHESH PANCHAL",
            "DocumentTable": "BUSINESSCORRESPONDENCE",
            "IsPublicVisible": false,
            "Source": "ONLINE",
            "CFTId": null,
            "CFTType": null,
            "NumberOfPages": 0,
            "UncommitedTID": 0,
            "CreatedDate": "0001-01-01T00:00:00",
            "FilerID": 0,
            "UserID": 0,
            "CreatedBy": 0,
            "IPAddress": null,
            "ModifiedBy": 0,
            "ModifiedIPAddress": null
        },
        {
            "DocumentID": 20185881,
            "DocumentTypeID": 27,
            "DocumentTypeName": "CONFIRMATION LETTER",
            "FileLocation": null,
            "FileLocationCorrespondence": "Certificates\\2021\\07\\0015385968_FilingCorrespondence_ConfirmationLetter.pdf",
            "FileLocationReceipt": null,
            "CorrespondenceFileName": "0015385968_FilingCorrespondence_ConfirmationLetter.pdf",
            "ReceiptFileName": null,
            "FilingNumber": 0,
            "TransactionID": 0,
            "WorkorderID": 0,
            "BusinessID": 0,
            "TrademarkID": 0,
            "RegistrationNo": 0,
            "IsOnline": false,
            "FilingDateTime": "2021-07-13T09:08:11",
            "FilerEmailAddress": null,
            "UserName": "MAHESH PANCHAL",
            "DocumentTable": "BUSINESSCORRESPONDENCE",
            "IsPublicVisible": false,
            "Source": "ONLINE",
            "CFTId": null,
            "CFTType": null,
            "NumberOfPages": 0,
            "UncommitedTID": 0,
            "CreatedDate": "0001-01-01T00:00:00",
            "FilerID": 0,
            "UserID": 0,
            "CreatedBy": 0,
            "IPAddress": null,
            "ModifiedBy": 0,
            "ModifiedIPAddress": null
        }
    ],
    [
        {
            "DocumentID": 16988307,
            "DocumentTypeID": 4,
            "DocumentTypeName": "ANNUAL REPORT - FULFILLED",
            "FileLocation": null,
            "FileLocationCorrespondence": "Certificates\\2020\\07\\0013765580_OnlineReport.pdf",
            "FileLocationReceipt": null,
            "CorrespondenceFileName": "0013765580_OnlineReport.pdf",
            "ReceiptFileName": null,
            "FilingNumber": 0,
            "TransactionID": 0,
            "WorkorderID": 0,
            "BusinessID": 0,
            "TrademarkID": 0,
            "RegistrationNo": 0,
            "IsOnline": false,
            "FilingDateTime": "2020-07-08T14:04:05",
            "FilerEmailAddress": null,
            "UserName": "",
            "DocumentTable": "BUSINESSCORRESPONDENCE",
            "IsPublicVisible": false,
            "Source": "ONLINE",
            "CFTId": null,
            "CFTType": null,
            "NumberOfPages": 0,
            "UncommitedTID": 0,
            "CreatedDate": "0001-01-01T00:00:00",
            "FilerID": 0,
            "UserID": 0,
            "CreatedBy": 0,
            "IPAddress": null,
            "ModifiedBy": 0,
            "ModifiedIPAddress": null
        }
    ],
    [
        {
            "DocumentID": 14032349,
            "DocumentTypeID": 4,
            "DocumentTypeName": "ANNUAL REPORT - FULFILLED",
            "FileLocation": null,
            "FileLocationCorrespondence": "Certificates\\2019\\06\\0012154837_OnlineReport.pdf",
            "FileLocationReceipt": null,
            "CorrespondenceFileName": "0012154837_OnlineReport.pdf",
            "ReceiptFileName": null,
            "FilingNumber": 0,
            "TransactionID": 0,
            "WorkorderID": 0,
            "BusinessID": 0,
            "TrademarkID": 0,
            "RegistrationNo": 0,
            "IsOnline": false,
            "FilingDateTime": "2019-06-28T10:12:51",
            "FilerEmailAddress": null,
            "UserName": "",
            "DocumentTable": "BUSINESSCORRESPONDENCE",
            "IsPublicVisible": false,
            "Source": "ONLINE",
            "CFTId": null,
            "CFTType": null,
            "NumberOfPages": 0,
            "UncommitedTID": 0,
            "CreatedDate": "0001-01-01T00:00:00",
            "FilerID": 0,
            "UserID": 0,
            "CreatedBy": 0,
            "IPAddress": null,
            "ModifiedBy": 0,
            "ModifiedIPAddress": null
        }
    ],
    [
        {
            "DocumentID": 11348264,
            "DocumentTypeID": 4,
            "DocumentTypeName": "ANNUAL REPORT - FULFILLED",
            "FileLocation": null,
            "FileLocationCorrespondence": "Certificates\\2018\\06\\0010740851_OnlineReport.pdf",
            "FileLocationReceipt": null,
            "CorrespondenceFileName": "0010740851_OnlineReport.pdf",
            "ReceiptFileName": null,
            "FilingNumber": 0,
            "TransactionID": 0,
            "WorkorderID": 0,
            "BusinessID": 0,
            "TrademarkID": 0,
            "RegistrationNo": 0,
            "IsOnline": false,
            "FilingDateTime": "2018-06-22T18:19:02",
            "FilerEmailAddress": null,
            "UserName": "",
            "DocumentTable": "BUSINESSCORRESPONDENCE",
            "IsPublicVisible": false,
            "Source": "ONLINE",
            "CFTId": null,
            "CFTType": null,
            "NumberOfPages": 0,
            "UncommitedTID": 0,
            "CreatedDate": "0001-01-01T00:00:00",
            "FilerID": 0,
            "UserID": 0,
            "CreatedBy": 0,
            "IPAddress": null,
            "ModifiedBy": 0,
            "ModifiedIPAddress": null
        }
    ],
    [
        {
            "DocumentID": 433558,
            "DocumentTypeID": 7,
            "DocumentTypeName": "BUSINESS DOCUMENT",
            "FileLocation": null,
            "FileLocationCorrespondence": "WSOSImage_PDFOnly\\14d4e396-fe7e-4b05-a988-78ca67bb09ba.pdf",
            "FileLocationReceipt": null,
            "CorrespondenceFileName": "14d4e396-fe7e-4b05-a988-78ca67bb09ba.pdf",
            "ReceiptFileName": null,
            "FilingNumber": 0,
            "TransactionID": 0,
            "WorkorderID": 0,
            "BusinessID": 0,
            "TrademarkID": 0,
            "RegistrationNo": 0,
            "IsOnline": false,
            "FilingDateTime": "2017-07-18T17:28:44",
            "FilerEmailAddress": null,
            "UserName": "BATCH JOB",
            "DocumentTable": "BUSINESSCORRESPONDENCE",
            "IsPublicVisible": false,
            "Source": "INHOUSE",
            "CFTId": null,
            "CFTType": null,
            "NumberOfPages": 0,
            "UncommitedTID": 0,
            "CreatedDate": "0001-01-01T00:00:00",
            "FilerID": 0,
            "UserID": 0,
            "CreatedBy": 0,
            "IPAddress": null,
            "ModifiedBy": 0,
            "ModifiedIPAddress": null
        }
    ],
    [
        {
            "DocumentID": 5895175,
            "DocumentTypeID": 7,
            "DocumentTypeName": "BUSINESS DOCUMENT",
            "FileLocation": null,
            "FileLocationCorrespondence": "WSOSImage\\df17b11f-c7ec-42c8-b938-2b45adbb9d07.pdf",
            "FileLocationReceipt": null,
            "CorrespondenceFileName": "df17b11f-c7ec-42c8-b938-2b45adbb9d07.pdf",
            "ReceiptFileName": null,
            "FilingNumber": 0,
            "TransactionID": 0,
            "WorkorderID": 0,
            "BusinessID": 0,
            "TrademarkID": 0,
            "RegistrationNo": 0,
            "IsOnline": false,
            "FilingDateTime": "2016-07-19T16:31:17",
            "FilerEmailAddress": null,
            "UserName": "BATCH JOB",
            "DocumentTable": "BUSINESSCORRESPONDENCE",
            "IsPublicVisible": false,
            "Source": "INHOUSE",
            "CFTId": null,
            "CFTType": null,
            "NumberOfPages": 0,
            "UncommitedTID": 0,
            "CreatedDate": "0001-01-01T00:00:00",
            "FilerID": 0,
            "UserID": 0,
            "CreatedBy": 0,
            "IPAddress": null,
            "ModifiedBy": 0,
            "ModifiedIPAddress": null
        }
    ]
]